LICENSE
MANIFEST.in
README.md
package.json
setup.py
custom_mantine_datepicker/DatePicker.py
custom_mantine_datepicker/__init__.py
custom_mantine_datepicker/_imports_.py
custom_mantine_datepicker/custom_mantine_datepicker.min.js
custom_mantine_datepicker/custom_mantine_datepicker.min.js.map
custom_mantine_datepicker/metadata.json
custom_mantine_datepicker/package-info.json
custom_mantine_datepicker.egg-info/PKG-INFO
custom_mantine_datepicker.egg-info/SOURCES.txt
custom_mantine_datepicker.egg-info/dependency_links.txt
custom_mantine_datepicker.egg-info/top_level.txt
custom_mantine_datepicker/theme/__init__.py
custom_mantine_datepicker/theme/default_colors.py