Metadata-Version: 2.1
Name: custom_mantine_datepicker
Version: 0.0.1
Summary: UNKNOWN
Home-page: https://github.com/snehilvj/dash-mantine-components
Author: Snehil Vijay <snehilvj@outlook.com>
Author-email: snehilvj@outlook.com
License: MIT
Platform: UNKNOWN
Classifier: Framework :: Dash
Classifier: Framework :: Flask
